{
  "$schema": "https://ui.shadcn.com/schema/registry.json",
  "name": "gjs-select",
  "homepage": "https://github.com/gokhanjs/gjs-select",
  "items": [
    {
      "name": "gjs-select",
      "type": "registry:ui",
      "description": "A feature-rich Select component built on Radix Popover and @tanstack/react-virtual. Single, multiple, and tags modes with built-in search and virtualized lists.",
      "dependencies": [
        "radix-ui",
        "@tanstack/react-virtual",
        "class-variance-authority",
        "lucide-react"
      ],
      "registryDependencies": ["utils"],
      "files": [
        {
          "path": "src/components/ui/gjs-select.tsx",
          "type": "registry:ui"
        }
      ]
    }
  ]
}
